{"nodes": [{"id": "object_model_ObjectRegistry", "label": "ObjectRegistry", "file_type": "code", "source_file": "src/object_model.h", "source_location": "12:34", "source_url": null, "captured_at": null, "author": null, "contributor": null}, {"id": "object_model_userMangleMethod", "label": "userMangleMethod", "file_type": "code", "source_file": "src/object_model.h", "source_location": "38:38", "source_url": null, "captured_at": null, "author": null, "contributor": null}, {"id": "object_model_UserTypeDef", "label": "UserTypeDef", "file_type": "code", "source_file": "src/object_model.h", "source_location": null, "source_url": null, "captured_at": null, "author": null, "contributor": null}], "edges": [{"source": "object_model_ObjectRegistry", "target": "parser_Program", "relation": "shares_data_with", "confidence": "EXTRACTED", "confidence_score": 1.0, "source_file": "src/object_model.h", "source_location": "13:13", "weight": 1.0}, {"source": "object_model_ObjectRegistry", "target": "type_desc_TypeDesc", "relation": "shares_data_with", "confidence": "EXTRACTED", "confidence_score": 1.0, "source_file": "src/object_model.h", "source_location": "23:28", "weight": 1.0}, {"source": "type_desc_TypeDesc", "target": "object_model_ObjectRegistry", "relation": "semantically_similar_to", "confidence": "INFERRED", "confidence_score": 0.75, "source_file": "src/object_model.h", "source_location": "23:28", "weight": 1.0}], "hyperedges": []}